gnutools/__init__.py
gnutools/utils/__init__.py
gnutools/utils/config_parser.py
gnutools/utils/printer.py
gnutools/www/__init__.py
gnutools/www/youtube.py
granate/__init__.py
granate/utils/__init__.py
granate/utils/config_parser.py
granate/utils/printer.py
granate/www/__init__.py
granate/www/youtube.py
granate-0.1a1.dist-info/METADATA
granate-0.1a1.dist-info/RECORD
granate-0.1a1.dist-info/WHEEL
granate-0.1a1.dist-info/top_level.txt
